social_auth_backend_epita/__init__.py
social_auth_backend_epita/backend.py
social_auth_backend_epita/pipeline.py
social_auth_backend_epita-1.0.2.dist-info/LICENSE
social_auth_backend_epita-1.0.2.dist-info/WHEEL
social_auth_backend_epita-1.0.2.dist-info/METADATA
social_auth_backend_epita-1.0.2.dist-info/RECORD
